llmtaskgrader/__init__.py
llmtaskgrader/cli/__init__.py
llmtaskgrader/cli/commands.py
llmtaskgrader/core/__init__.py
llmtaskgrader/core/criteria.py
llmtaskgrader/core/grader.py
llmtaskgrader/core/models.py
llmtaskgrader/llm/__init__.py
llmtaskgrader/llm/bailian.py
llmtaskgrader/llm/prompts.py
llmtaskgrader/mcp/__init__.py
llmtaskgrader/mcp/server.py
llmtaskgrader/utils/__init__.py
llmtaskgrader/utils/env.py
llmtaskgrader-0.1.0.dist-info/METADATA
llmtaskgrader-0.1.0.dist-info/WHEEL
llmtaskgrader-0.1.0.dist-info/entry_points.txt
llmtaskgrader-0.1.0.dist-info/licenses/LICENSE
llmtaskgrader-0.1.0.dist-info/RECORD
