Metadata-Version: 2.4
Name: llmtaskgrader
Version: 0.1.0
Summary: LLM任务难度评分工具，支持百炼、OpenRouter和Gemini等大模型
Project-URL: Homepage, https://github.com/yourusername/llmtaskgrader
Project-URL: Bug Tracker, https://github.com/yourusername/llmtaskgrader/issues
Author-email: Your Name <your.email@example.com>
License: MIT License
License-File: LICENSE
Classifier: License :: OSI Approved :: MIT License
Classifier: Operating System :: OS Independent
Classifier: Programming Language :: Python :: 3
Requires-Python: >=3.7
Requires-Dist: click>=8.0.0
Requires-Dist: httpx>=0.23.0
Requires-Dist: pydantic>=1.9.0
Requires-Dist: rich>=10.0.0
Provides-Extra: dev
Requires-Dist: black>=22.0.0; extra == 'dev'
Requires-Dist: isort>=5.0.0; extra == 'dev'
Requires-Dist: mypy>=0.9.0; extra == 'dev'
Requires-Dist: pytest>=7.0.0; extra == 'dev'
